zx_db_manager/__init__.py
zx_db_manager/mysql_cloud.py
zx_db_manager-0.1.2.dist-info/METADATA
zx_db_manager-0.1.2.dist-info/WHEEL
zx_db_manager-0.1.2.dist-info/top_level.txt
zx_db_manager-0.1.2.dist-info/RECORD
